kgprim/__init__.py
kgprim/core.py
kgprim/motions.py
kgprim/values.py
kgprim/ct/__init__.py
kgprim/ct/frommotions.py
kgprim/ct/metadata.py
kgprim/ct/models.py
kgprim/ct/backend/__init__.py
kgprim/ct/backend/numeric.py
kgprim/ct/backend/symbolic.py
kgprim/ct/repr/__init__.py
kgprim/ct/repr/homogeneous.py
kgprim/ct/repr/mxcommon.py
kgprim/ct/repr/mxrepr.py
kgprim/ct/repr/spatial.py
motiondsl/__init__.py
motiondsl/motiondsl.py
motiondsl/motiondsl.tx
kgprim-0.1.1.dist-info/LICENSE
kgprim-0.1.1.dist-info/METADATA
kgprim-0.1.1.dist-info/WHEEL
kgprim-0.1.1.dist-info/top_level.txt
kgprim-0.1.1.dist-info/RECORD
