Metadata-Version: 2.1
Name: kgprim
Version: 0.1.1
Summary: Kinematics/geometric primitives
Author-email: Marco Frigerio <marco.frigerio17@pm.me>
License: Copyright (c) 2020-2024, Marco Frigerio
Project-URL: home, https://github.com/mfrigerio17/kgprim
Requires-Python: >=3.3
License-File: LICENSE
Requires-Dist: networkx
Requires-Dist: numpy
Requires-Dist: sympy
Requires-Dist: textX
